{
  "trade_date": "2026-04-10",
  "source_file": "C:\\Users\\wdyab\\Desktop\\wdy\\stocks\\reports\\patterns_all_2026-04-10.csv",
  "section_preview": "### 2026.4.10\n\n| 梯队 | 股票代码 | 股票名称 | 行业/主线 | 符合模式/背离 | 五日分数 | 五日均分 | TradingView标签 | 推荐理由 |\n| ---- | -------- | -------- | --------- | ------------- | -------- | -------: | --------------- | -------- |\n| 第一梯队 | 002950 | 奥美医疗 | 未分类 | pattern 1 | 0.2909 / 0.6030 / 0.5121 / 0.4909 / 0.6485 | 0.5091 | strong_buy | pattern 1 配合 strong_buy，五日均分 0.5091，先按技术强度归入观察池。 |\n| 第一梯队 | 603906 | 龙蟠科技 | 电池 | pattern 1 | 0.4455 / 0.3788 / 0.5121 / 0.5121 / 0.5121 | 0.4721 | strong_buy | 电池 方向里，pattern 1 配合 strong_buy，五日均分 0.4721，优先关注形态和强度同时成立的标的。 |\n| 第一梯队 | 002705 | 新宝股份 | 未分类 | pattern 1 | 0.0879 / 0.4242 / 0.5576 / 0.4667 / 0.5576 | 0.4188 | strong_buy | pattern 1 配合 strong_buy，五日均分 0.4188，先按技术强度归入观察池。 |\n| 第一梯队 | 002850 | 科达利 | 电池 | pattern 1 | 0.2182 / 0.3545 / 0.5364 / 0.5576 / 0.5121 | 0.4358 | strong_buy | 电池 方向里，pattern 1 配合 strong_buy，五日均分 0.4358，优先关注形态和强度同时成立的标的。 |\n| 第一梯队 | 600872 | 中炬高新 | 未分类 | pattern 2 | 0.3091 / 0.4909 / 0.6030 / 0.4667 / 0.6030 | 0.4945 | strong_buy | pattern 2 配合 strong_buy，五日均分 0.4945，先按技术强度归入观察池。 |\n| 第一梯队 | 600769 | 祥龙电业 | 未分类 | pattern 1 | 0.4242 / -0.1788 / 0.4909 / 0.6030 / 0.5121 | 0.3703 | strong_buy | pattern 1 配合 strong_buy，五日均分 0.3703，先按技术强度归入观察池。 |\n| 第一梯队 | 603076 | 乐惠国际 | 未分类 | pattern 1 + 顶背离 | 0.4455 / 0.6030 / 0.4667 / 0.3545 / 0.4909 | 0.4721 | buy | pattern 1 配合 buy，五日均分 0.4721，近15日出现顶背离，先结合位置判断信号有效性。 |\n| 第一梯队 | 601825 | 沪农商行 | 未分类 | pattern 2 | 0.3091 / 0.4242 / 0.4000 / 0.2667 / 0.6030 | 0.4006 | strong_buy | pattern 2 配合 strong_buy，五日均分 0.4006，先按技术强度归入观察池。 |\n| 第一梯队 | 002579 | 中京电子 | 算力硬件 | pattern 1 + 底背离 | 0.4667 / 0.6030 / 0.4667 / 0.2636 / 0.4000 | 0.4400 | buy | 算力硬件 方向里，pattern 1 配合 buy，五日均分 0.4400，近15日出现底背离，先结合位置判断信号有效性。 |\n| 第一梯队 | 603288 | 海天味业 | 未分类 | pattern 2 + 底背离 | 0.3091 / 0.3545 / 0.4000 / 0.4000 / 0.5576 | 0.4042 | strong_buy | pattern 2 配合 strong_buy，五日均分 0.4042，近15日出现底背离，先结合位置判断信号有效性。 |\n| 第一梯队 | 601000 | 唐山港 | 未分类 | pattern 2 + 顶背离 | 0.2636 / 0.4000 / 0.3545 / 0.3545 / 0.5576 | 0.3861 | strong_buy | pattern 2 配合 strong_buy，五日均分 0.3861，近15日出现顶背离，先结合位置判断信号有效性。 |\n| 第一梯队 | 000729 | 燕京啤酒 | 未分类 | pattern 2 + 顶背离 | 0.6030 / 0.5121 / 0.4667 / 0.4000 / 0.4455 | 0.4855 | buy | pattern 2 配合 buy，五日均分 0.4855，近15日出现顶背离，先结合位置判断信号有效性。 |\n| 第一梯队 | 600539 | 狮头股份 | 未分类 | pattern 4 | 0.4909 / 0.4909 / 0.5121 / 0.5121 / 0.5576 | 0.5127 | strong_buy | pattern 4 配合 strong_buy，五日均分 0.5127，先按技术强度归入观察池。 |\n| 第一梯队 | 002432 | 九安医疗 | 未分类 | pattern 4 | 0.4000 / 0.4909 / 0.5576 / 0.3545 / 0.6030 | 0.4812 | strong_buy | pattern 4 配合 strong_buy，五日均分 0.4812，先按技术强度归入观察池。 |\n| 第一梯队 | 603118 | 共进股份 | 算力硬件 | pattern 1 + 顶背离 | 0.4455 / 0.5576 / 0.4667 / 0.4212 / 0.2182 | 0.4218 | buy | 算力硬件 方向里，pattern 1 配合 buy，五日均分 0.4218，近15日出现顶背离，先结合位置判断信号有效性。 |\n| 第一梯队 | 603222 | 济民健康 | 未分类 | pattern 2 | 0.5576 / 0.5576 / 0.3091 / 0.4000 / 0.4455 | 0.4539 | buy | pattern 2 配合 buy，五日均分 0.4539，先按技术强度归入观察池。 |\n| 第一梯队 | 002832 | 比音勒芬 | 未分类 | pattern 3 + 顶背离 | 0.3788 / 0.2667 / 0.3758 / 0.4667 / 0.4212 | 0.3818 | buy | pattern 3 配合 buy，五日均分 0.3818，近15日出现顶背离，先结合位置判断信号有效性。 |\n| 第一梯队 | 600901 | 江苏金租 | 未分类 | pattern 2 + 顶背离 | 0.4000 / 0.4242 / 0.4667 / 0.6030 / 0.3091 | 0.4406 | buy | pattern 2 配合 buy，五日均分 0.4406，近15日出现顶背离，先结合位置判断信号有效性。 |\n| 第一梯队 | 600664 | 哈药股份 | 未分类 | pattern 2 | 0.1121 / 0.6030 / 0.3545 / 0.4000 / 0.4455 | 0.3830 | buy | pattern 2 配合 buy，五日均分 0.3830，先按技术强度归入观察池。 |\n| 第一梯队 | 601083 | 锦江航运 | 未分类 | pattern 2 | 0.4455 / 0.4455 / 0.3091 / 0.3545 / 0.4000 | 0.3909 | buy | pattern 2 配合 buy，五日均分 0.3909，先按技术强度归入观察池。 |\n| 第一梯队 | 605178 | 时空科技 | 未分类 | pattern 2 | -0.0667 / 0.4667 / 0.6030 / 0.5121 / 0.3091 | 0.3648 | buy | pattern 2 配合 buy，五日均分 0.3648，先按技术强度归入观察池。 |\n| 第一梯队 | 600015 | 华夏银行 | 未分类 | pattern 2 | 0.3545 / 0.4455 / 0.4000 / 0.4000 / 0.1758 | 0.3552 | buy | pattern 2 配合 buy，五日均分 0.3552，先按技术强度归入观察池。 |\n\n| 梯队 | 股票代码 | 股票名称 | 行业/主线 | 符合模式/背离 | 五日分数 | 五日均分 | TradingView标签 | 推荐理由 |\n| ---- | -------- | -------- | --------- | ------------- | -------- | -------: | --------------- | -------- |\n| 第三梯队 | 003026 | 中晶科技 | 算力硬件 | pattern 1 + 底背离 | -0.1333 / -0.1121 / 0.5576 / 0.3758 / 0.6030 | 0.2582 | strong_buy | 算力硬件 方向里，pattern 1 配合 strong_buy，五日均分 0.2582，近15日出现底背离，先结合位置判断信号有效性。 |\n| 第三梯队 | 003026 | 中晶科技 | 算力硬件 | pattern 2 + 底背离 | -0.1333 / -0.1121 / 0.5576 / 0.3758 / 0.6030 | 0.2582 | strong_buy | 算力硬件 方向里，pattern 2 配合 strong_buy，五日均分 0.2582，近15日出现底背离，先结合位置判断信号有效性。 |\n| 第三梯队 | 002692 | 远程股份 | 未分类 | pattern 1 | -0.2455 / -0.0212 / 0.6030 / 0.5576 / 0.4212 | 0.2630 | buy | pattern 1 配合 buy，五日均分 0.2630，先按技术强度归入观察池。 |\n| 第三梯队 | 000989 | 中证全指可选消费指数 | 未分类 | pattern 2 + 底背离 | 0.2424 / 0.2879 / 0.2424 / 0.2424 / 0.3788 | 0.2788 | buy | pattern 2 配合 buy，五日均分 0.2788，近15日出现底背离，先结合位置判断信号有效性。 |\n| 第三梯队 | 000989 | 中证全指可选消费指数 | 未分类 | pattern 2 + 底背离 | 0.2424 / 0.2879 / 0.2424 / 0.2424 / 0.3788 | 0.2788 | buy | pattern 2 配合 buy，五日均分 0.2788，近15日出现底背离，先结合位置判断信号有效性。 |\n| 第三梯队 | 000989 | 中证全指可选消费指数 | 未分类 | pattern 2 + 底背离 | 0.2424 / 0.2879 / 0.2424 / 0.2424 / 0.3788 | 0.2788 | buy | pattern 2 配合 buy，五日均分 0.2788，近15日出现底背离，先结合位置判断信号有效性。 |\n| 第三梯队 | 000989 | 中证全指可选消费指数 | 未分类 | pattern 2 + 底背离 | 0.2424 / 0.2879 / 0.2424 / 0.2424 / 0.3788 | 0.2788 | buy | pattern 2 配合 buy，五日均分 0.2788，近15日出现底背离，先结合位置判断信号有效性。 |\n| 第三梯队 | 000989 | 中证全指可选消费指数 | 未分类 | pattern 2 + 底背离 | 0.2424 / 0.2879 / 0.2424 / 0.2424 / 0.3788 | 0.2788 | buy | pattern 2 配合 buy，五日均分 0.2788，近15日出现底背离，先结合位置判断信号有效性。 |\n\n总结：当日共筛出 30 只股票；算力硬件 方向占 4 只，仍是更集中的主线；第一梯队有 22 只，强度层次偏集中；近几日持续重复出现的股票有 002579, 002850, 003026, 603118, 603906；本次记录日期为 2026-04-10，后续可继续观察重复入选个股是否开始收敛到少数核心票。\n",
  "picks_path": "C:\\Users\\wdyab\\Desktop\\wdy\\stocks\\选股.md",
  "candidate_count": 30
}